{
"type": "FeatureCollection",
"crs": { "type": "name", "properties": { "name": "urn:ogc:def:crs:OGC:1.3:CRS84" } },
                                                                                                                                  
"features": [
{ "type": "Feature", "properties": { "Name": "Code for Eindhoven", "description": "Contact: info@codefor.nl", "timestamp": null, "begin": null, "end": null, "altitudeMode": null, "tessellate": -1, "extrude": -1, "visibility": -1, "drawOrder": null, "icon": null }, "geometry": { "type": "Point", "coordinates": [ 5.4697225, 51.441642, 0.0 ] } },
{ "type": "Feature", "properties": { "Name": "Helsinki Open Software Development Team", "description": "http:\/\/dev.hel.fi\/", "timestamp": null, "begin": null, "end": null, "altitudeMode": null, "tessellate": -1, "extrude": -1, "visibility": -1, "drawOrder": null, "icon": null }, "geometry": { "type": "Point", "coordinates": [ 24.938379, 60.1698557, 0.0 ] } },
{ "type": "Feature", "properties": { "Name": "Amsterdam", "description": "Contact: Johan Groenen (johan.groenen@gmail.com)", "timestamp": null, "begin": null, "end": null, "altitudeMode": null, "tessellate": -1, "extrude": -1, "visibility": -1, "drawOrder": null, "icon": null }, "geometry": { "type": "Point", "coordinates": [ 4.8951679, 52.3702157, 0.0 ] } }
]
}
